app/__init__.py
app/callback.py
app/cli.py
app/commands/__init__.py
app/commands/add.py
app/commands/delete.py
app/commands/init.py
app/commands/list.py
app/commands/status.py
app/core/__init__.py
app/core/errors.py
app/core/models.py
app/core/repository.py
app/core/storage.py
app/core/utils.py
notecli-0.1.1.dist-info/METADATA
notecli-0.1.1.dist-info/WHEEL
notecli-0.1.1.dist-info/entry_points.txt
notecli-0.1.1.dist-info/RECORD
